[{
  "_id": {
    "$oid": "67464e549702a9cd860131b4"
  },
  "MaintenanceID": 101,
  "NextMaintenance": "2025-08-22",
  "Type": "Corrective",
  "Employee_Incharge": 6651,
  "MachineryID": 55,
  "VehicleID": "null"
},
{
  "_id": {
    "$oid": "67464e549702a9cd860131b5"
  },
  "MaintenanceID": 105,
  "NextMaintenance": "2025-03-25",
  "Type": "Planned",
  "Employee_Incharge": 6651,
  "MachineryID": 41,
  "VehicleID": "null"
},
{
  "_id": {
    "$oid": "67464e549702a9cd860131b6"
  },
  "MaintenanceID": 108,
  "NextMaintenance": "2025-04-26",
  "Type": "Corrective",
  "Employee_Incharge": 5206,
  "MachineryID": "null",
  "VehicleID": 26
},
{
  "_id": {
    "$oid": "67464e549702a9cd860131b7"
  },
  "MaintenanceID": 116,
  "NextMaintenance": "2025-10-05",
  "Type": "Corrective",
  "Employee_Incharge": 9223,
  "MachineryID": 28,
  "VehicleID": "null"
},
{
  "_id": {
    "$oid": "67464e549702a9cd860131b8"
  },
  "MaintenanceID": 118,
  "NextMaintenance": "2025-10-09",
  "Type": "Planned",
  "Employee_Incharge": 6651,
  "MachineryID": "null",
  "VehicleID": 11
},
{
  "_id": {
    "$oid": "67464e549702a9cd860131b9"
  },
  "MaintenanceID": 119,
  "NextMaintenance": "2025-05-10",
  "Type": "Breakdown",
  "Employee_Incharge": 5424,
  "MachineryID": "null",
  "VehicleID": 67
},
{
  "_id": {
    "$oid": "67464e549702a9cd860131ba"
  },
  "MaintenanceID": 120,
  "NextMaintenance": "2025-06-03",
  "Type": "Breakdown",
  "Employee_Incharge": 6308,
  "MachineryID": 55,
  "VehicleID": "null"
},
{
  "_id": {
    "$oid": "67464e549702a9cd860131bb"
  },
  "MaintenanceID": 121,
  "NextMaintenance": "2025-05-21",
  "Type": "Breakdown",
  "Employee_Incharge": 7626,
  "MachineryID": "null",
  "VehicleID": 76
},
{
  "_id": {
    "$oid": "67464e549702a9cd860131bc"
  },
  "MaintenanceID": 122,
  "NextMaintenance": "2024-12-02",
  "Type": "Corrective",
  "Employee_Incharge": 4479,
  "MachineryID": 70,
  "VehicleID": "null"
},
{
  "_id": {
    "$oid": "67464e549702a9cd860131bd"
  },
  "MaintenanceID": 124,
  "NextMaintenance": "2025-06-11",
  "Type": "Corrective",
  "Employee_Incharge": 3579,
  "MachineryID": "null",
  "VehicleID": 31
},
{
  "_id": {
    "$oid": "67464e549702a9cd860131be"
  },
  "MaintenanceID": 128,
  "NextMaintenance": "2025-08-26",
  "Type": "Corrective",
  "Employee_Incharge": 3484,
  "MachineryID": "null",
  "VehicleID": 83
},
{
  "_id": {
    "$oid": "67464e549702a9cd860131bf"
  },
  "MaintenanceID": 132,
  "NextMaintenance": "2024-12-09",
  "Type": "Planned",
  "Employee_Incharge": 4479,
  "MachineryID": 55,
  "VehicleID": "null"
},
{
  "_id": {
    "$oid": "67464e549702a9cd860131c0"
  },
  "MaintenanceID": 135,
  "NextMaintenance": "2025-01-15",
  "Type": "Breakdown",
  "Employee_Incharge": 3484,
  "MachineryID": "null",
  "VehicleID": 98
},
{
  "_id": {
    "$oid": "67464e549702a9cd860131c1"
  },
  "MaintenanceID": 137,
  "NextMaintenance": "2025-02-28",
  "Type": "Breakdown",
  "Employee_Incharge": 9245,
  "MachineryID": 48,
  "VehicleID": "null"
},
{
  "_id": {
    "$oid": "67464e549702a9cd860131c2"
  },
  "MaintenanceID": 138,
  "NextMaintenance": "2025-01-08",
  "Type": "Planned",
  "Employee_Incharge": 4355,
  "MachineryID": "null",
  "VehicleID": 62
},
{
  "_id": {
    "$oid": "67464e549702a9cd860131c3"
  },
  "MaintenanceID": 139,
  "NextMaintenance": "2025-02-01",
  "Type": "Planned",
  "Employee_Incharge": 7626,
  "MachineryID": "null",
  "VehicleID": 58
},
{
  "_id": {
    "$oid": "67464e549702a9cd860131c4"
  },
  "MaintenanceID": 140,
  "NextMaintenance": "2025-11-10",
  "Type": "Planned",
  "Employee_Incharge": 9571,
  "MachineryID": "null",
  "VehicleID": 16
},
{
  "_id": {
    "$oid": "67464e549702a9cd860131c5"
  },
  "MaintenanceID": 142,
  "NextMaintenance": "2025-07-04",
  "Type": "Breakdown",
  "Employee_Incharge": 6937,
  "MachineryID": 68,
  "VehicleID": "null"
},
{
  "_id": {
    "$oid": "67464e549702a9cd860131c6"
  },
  "MaintenanceID": 147,
  "NextMaintenance": "2025-01-12",
  "Type": "Breakdown",
  "Employee_Incharge": 7626,
  "MachineryID": "null",
  "VehicleID": 16
},
{
  "_id": {
    "$oid": "67464e549702a9cd860131c7"
  },
  "MaintenanceID": 149,
  "NextMaintenance": "2025-05-29",
  "Type": "Corrective",
  "Employee_Incharge": 9659,
  "MachineryID": 48,
  "VehicleID": "null"
},
{
  "_id": {
    "$oid": "67464e549702a9cd860131c8"
  },
  "MaintenanceID": 163,
  "NextMaintenance": "2025-02-10",
  "Type": "Planned",
  "Employee_Incharge": 9876,
  "MachineryID": "null",
  "VehicleID": 79
},
{
  "_id": {
    "$oid": "67464e549702a9cd860131c9"
  },
  "MaintenanceID": 170,
  "NextMaintenance": "2025-10-07",
  "Type": "Planned",
  "Employee_Incharge": 2350,
  "MachineryID": 61,
  "VehicleID": "null"
},
{
  "_id": {
    "$oid": "67464e549702a9cd860131ca"
  },
  "MaintenanceID": 171,
  "NextMaintenance": "2024-12-21",
  "Type": "Breakdown",
  "Employee_Incharge": 7274,
  "MachineryID": "null",
  "VehicleID": 39
},
{
  "_id": {
    "$oid": "67464e549702a9cd860131cb"
  },
  "MaintenanceID": 173,
  "NextMaintenance": "2024-12-18",
  "Type": "Planned",
  "Employee_Incharge": 7136,
  "MachineryID": "null",
  "VehicleID": 26
},
{
  "_id": {
    "$oid": "67464e549702a9cd860131cc"
  },
  "MaintenanceID": 180,
  "NextMaintenance": "2024-12-31",
  "Type": "Corrective",
  "Employee_Incharge": 5284,
  "MachineryID": 66,
  "VehicleID": "null"
},
{
  "_id": {
    "$oid": "67464e549702a9cd860131cd"
  },
  "MaintenanceID": 186,
  "NextMaintenance": "2025-10-27",
  "Type": "Breakdown",
  "Employee_Incharge": 6651,
  "MachineryID": 11,
  "VehicleID": "null"
},
{
  "_id": {
    "$oid": "67464e549702a9cd860131ce"
  },
  "MaintenanceID": 190,
  "NextMaintenance": "2024-11-23",
  "Type": "Corrective",
  "Employee_Incharge": 9876,
  "MachineryID": "null",
  "VehicleID": 92
},
{
  "_id": {
    "$oid": "67464e549702a9cd860131cf"
  },
  "MaintenanceID": 193,
  "NextMaintenance": "2025-07-29",
  "Type": "Corrective",
  "Employee_Incharge": 3490,
  "MachineryID": 55,
  "VehicleID": "null"
},
{
  "_id": {
    "$oid": "67464e549702a9cd860131d0"
  },
  "MaintenanceID": 195,
  "NextMaintenance": "2025-07-31",
  "Type": "Planned",
  "Employee_Incharge": 1615,
  "MachineryID": 12,
  "VehicleID": "null"
},
{
  "_id": {
    "$oid": "67464e549702a9cd860131d1"
  },
  "MaintenanceID": 196,
  "NextMaintenance": "2025-07-06",
  "Type": "Breakdown",
  "Employee_Incharge": 9245,
  "MachineryID": "null",
  "VehicleID": 56
}]